LICENSE
MANIFEST.in
readme.md
setup.py
sklearn_recommender/__init__.py
sklearn_recommender/estimators.py
sklearn_recommender/glove.py
sklearn_recommender/helper.py
sklearn_recommender/ml_helper.py
sklearn_recommender/recommender.py
sklearn_recommender/transformer.py
sklearn_recommender.egg-info/PKG-INFO
sklearn_recommender.egg-info/SOURCES.txt
sklearn_recommender.egg-info/dependency_links.txt
sklearn_recommender.egg-info/not-zip-safe
sklearn_recommender.egg-info/requires.txt
sklearn_recommender.egg-info/top_level.txt