Metadata-Version: 2.1
Name: sklearn-recommender
Version: 0.1.2
Summary: Sklearn Extension to integration recommender functions
Home-page: https://github.com/felixnext/sklearn-recommender
Author: Felix Geilert
License: MIT License
Keywords: recommender systems
Platform: UNKNOWN
